runa/__init__.py
runa/api.py
runa/cli.py
runa/models.py
runa/runa.py
runa/utils.py
runa-0.2.9.dist-info/METADATA
runa-0.2.9.dist-info/RECORD
runa-0.2.9.dist-info/WHEEL
runa-0.2.9.dist-info/entry_points.txt
runa-0.2.9.dist-info/top_level.txt
