Metadata-Version: 2.1
Name: runa
Version: 0.2.9
Summary: Librería para uso de WS del Bus Gubernamental de Ecuador
Home-page: https://github.com/ovnicraft/runa
Author: Cristian Salamea
Author-email: cristian.salamea@gmail.com
License: MIT license
Keywords: runa webservices ecuador bgs
Platform: UNKNOWN
Classifier: Development Status :: 3 - Alpha
Classifier: Intended Audience :: Developers
Classifier: License :: OSI Approved :: MIT License
Classifier: Natural Language :: English
Classifier: Programming Language :: Python :: 2.7
Classifier: Programming Language :: Python :: 3
Classifier: Programming Language :: Python :: 3.3
Classifier: Programming Language :: Python :: 3.4
Classifier: Programming Language :: Python :: 3.5
Classifier: Programming Language :: Python :: 3.6
Requires-Dist: Click (>=6.0)
Requires-Dist: suds2 (==0.7.1)
